iugupy/__init__.py
iugupy/client.py
iugupy/config.py
iugupy/errors.py
iugupy/py.typed
iugupy/resources/__init__.py
iugupy/resources/base.py
iugupy/resources/customers.py
iugupy/resources/invoices.py
iugupy/resources/plans.py
iugupy/resources/subscriptions.py
iugupy-0.1.0.dist-info/WHEEL
iugupy-0.1.0.dist-info/METADATA
iugupy-0.1.0.dist-info/RECORD
