Metadata-Version: 2.3
Name: iugupy
Version: 0.1.0
Summary: Python REST APIs for Iugu
Author: Ramon Soares
Author-email: Ramon Soares <ramongsoares@gmail.com>
Requires-Dist: requests>=2.32.5
Requires-Dist: pytest>=8.0.0 ; extra == 'dev'
Requires-Dist: black>=24.0.0 ; extra == 'dev'
Requires-Python: >=3.13
Provides-Extra: dev
